giotto_tda_nightly.libs/libgomp-a34b3233.so.1.0.0
giotto_tda_nightly-20220825.5.dist-info/top_level.txt
giotto_tda_nightly-20220825.5.dist-info/WHEEL
giotto_tda_nightly-20220825.5.dist-info/METADATA
giotto_tda_nightly-20220825.5.dist-info/RECORD
giotto_tda_nightly-20220825.5.dist-info/LICENSE
gtda/_version.py
gtda/base.py
gtda/__init__.py
gtda/pipeline.py
gtda/diagrams/representations.py
gtda/diagrams/_features.py
gtda/diagrams/distance.py
gtda/diagrams/_metrics.py
gtda/diagrams/preprocessing.py
gtda/diagrams/__init__.py
gtda/diagrams/features.py
gtda/diagrams/_utils.py
gtda/diagrams/tests/test_preprocessing.py
gtda/diagrams/tests/test_features_representations.py
gtda/diagrams/tests/test_distance.py
gtda/diagrams/tests/__init__.py
gtda/local_homology/simplicial.py
gtda/local_homology/__init__.py
gtda/local_homology/tests/test_simplicial.py
gtda/local_homology/tests/__init__.py
gtda/tests/test_common.py
gtda/tests/test_pipeline.py
gtda/tests/__init__.py
gtda/point_clouds/__init__.py
gtda/point_clouds/rescaling.py
gtda/point_clouds/tests/test_rescaling.py
gtda/point_clouds/tests/__init__.py
gtda/metaestimators/collection_transformer.py
gtda/metaestimators/__init__.py
gtda/metaestimators/tests/test_collection_transformer.py
gtda/metaestimators/tests/__init__.py
gtda/externals/__init__.py
gtda/externals/modules/gtda_wasserstein.cpython-38-x86_64-linux-gnu.so
gtda/externals/modules/gtda_witness_complex.cpython-38-x86_64-linux-gnu.so
gtda/externals/modules/gtda_periodic_cubical_complex.cpython-38-x86_64-linux-gnu.so
gtda/externals/modules/gtda_sparse_rips_complex.cpython-38-x86_64-linux-gnu.so
gtda/externals/modules/gtda_cech_complex.cpython-38-x86_64-linux-gnu.so
gtda/externals/modules/gtda_simplex_tree.cpython-38-x86_64-linux-gnu.so
gtda/externals/modules/gtda_bottleneck.cpython-38-x86_64-linux-gnu.so
gtda/externals/modules/gtda_persistent_cohomology.cpython-38-x86_64-linux-gnu.so
gtda/externals/modules/gtda_cubical_complex.cpython-38-x86_64-linux-gnu.so
gtda/externals/modules/gtda_strong_witness_complex.cpython-38-x86_64-linux-gnu.so
gtda/externals/python/strong_witness_complex_interface.py
gtda/externals/python/cubical_complex_interface.py
