Metadata-Version: 2.1
Name: giotto-tda-nightly
Version: 20220825.5
Summary: Toolbox for Machine Learning using Topological Data Analysis.
Home-page: https://github.com/giotto-ai/giotto-tda
Download-URL: https://github.com/giotto-ai/giotto-tda/tarball/v20220825.5
Maintainer: Umberto Lupo, Wojciech Reise
Maintainer-email: maintainers@giotto.ai
License: GNU AGPLv3
Keywords: machine learning,topological data analysis,persistent homology,persistence diagrams,Mapper
Classifier: Intended Audience :: Science/Research
Classifier: Intended Audience :: Developers
Classifier: License :: OSI Approved
Classifier: Programming Language :: C++
Classifier: Programming Language :: Python
Classifier: Topic :: Software Development
Classifier: Topic :: Scientific/Engineering
Classifier: Operating System :: Microsoft :: Windows
Classifier: Operating System :: POSIX
Classifier: Operating System :: Unix
Classifier: Operating System :: MacOS
Classifier: Programming Language :: Python :: 3.7
Classifier: Programming Language :: Python :: 3.8
Classifier: Programming Language :: Python :: 3.9
Classifier: Programming Language :: Python :: 3.10
License-File: LICENSE
Requires-Dist: numpy (>=1.19.1)
Requires-Dist: scipy (>=1.5.0)
Requires-Dist: joblib (>=0.16.0)
Requires-Dist: scikit-learn (>=0.23.1)
Requires-Dist: giotto-ph (>=0.2.1)
Requires-Dist: pyflagser (>=0.4.3)
Requires-Dist: igraph (>=0.9.8)
Requires-Dist: plotly (>=4.8.2)
Requires-Dist: ipywidgets (>=7.5.1)
Provides-Extra: dev
Requires-Dist: jupyter-contrib-nbextensions ; extra == 'dev'
Requires-Dist: sphinx-issues ; extra == 'dev'
Requires-Dist: pytest-cov ; extra == 'dev'
Requires-Dist: pandas ; extra == 'dev'
Requires-Dist: sphinx-rtd-theme ; extra == 'dev'
Requires-Dist: pytest-benchmark ; extra == 'dev'
Requires-Dist: openml ; extra == 'dev'
Requires-Dist: nbconvert ; extra == 'dev'
Requires-Dist: flake8 ; extra == 'dev'
Requires-Dist: pytest-azurepipelines ; extra == 'dev'
Requires-Dist: hypothesis ; extra == 'dev'
Requires-Dist: sphinx ; extra == 'dev'
Requires-Dist: numpydoc ; extra == 'dev'
Requires-Dist: pytest ; extra == 'dev'
Provides-Extra: doc
Requires-Dist: openml ; extra == 'doc'
Requires-Dist: sphinx ; extra == 'doc'
Requires-Dist: nbconvert ; extra == 'doc'
Requires-Dist: sphinx-issues ; extra == 'doc'
Requires-Dist: sphinx-rtd-theme ; extra == 'doc'
Requires-Dist: numpydoc ; extra == 'doc'
Provides-Extra: examples
Requires-Dist: jupyter ; extra == 'examples'
Requires-Dist: pandas ; extra == 'examples'
Requires-Dist: openml ; extra == 'examples'
Requires-Dist: matplotlib ; extra == 'examples'
Requires-Dist: gensim ; extra == 'examples'
Requires-Dist: umap-learn ; extra == 'examples'
Provides-Extra: tests
Requires-Dist: pandas ; extra == 'tests'
Requires-Dist: pytest ; extra == 'tests'
Requires-Dist: pytest-cov ; extra == 'tests'
Requires-Dist: pytest-azurepipelines ; extra == 'tests'
Requires-Dist: pytest-benchmark ; extra == 'tests'
Requires-Dist: jupyter-contrib-nbextensions ; extra == 'tests'
Requires-Dist: flake8 ; extra == 'tests'
Requires-Dist: hypothesis ; extra == 'tests'
